fds/__init__.py
fds/sdk/__init__.py
fds/sdk/ProcuretoPaySCIM/__init__.py
fds/sdk/ProcuretoPaySCIM/api_client.py
fds/sdk/ProcuretoPaySCIM/configuration.py
fds/sdk/ProcuretoPaySCIM/exceptions.py
fds/sdk/ProcuretoPaySCIM/model_utils.py
fds/sdk/ProcuretoPaySCIM/rest.py
fds/sdk/ProcuretoPaySCIM/api/__init__.py
fds/sdk/ProcuretoPaySCIM/api/groups_api.py
fds/sdk/ProcuretoPaySCIM/api/locations_api.py
fds/sdk/ProcuretoPaySCIM/api/products_api.py
fds/sdk/ProcuretoPaySCIM/api/schemas_api.py
fds/sdk/ProcuretoPaySCIM/api/server_configuration_api.py
fds/sdk/ProcuretoPaySCIM/api/users_api.py
fds/sdk/ProcuretoPaySCIM/api/vermilion_groups_api.py
fds/sdk/ProcuretoPaySCIM/api/vermilion_users_api.py
fds/sdk/ProcuretoPaySCIM/apis/__init__.py
fds/sdk/ProcuretoPaySCIM/model/__init__.py
fds/sdk/ProcuretoPaySCIM/model/error.py
fds/sdk/ProcuretoPaySCIM/model/group_resource.py
fds/sdk/ProcuretoPaySCIM/model/group_resource_list.py
fds/sdk/ProcuretoPaySCIM/model/group_resource_members.py
fds/sdk/ProcuretoPaySCIM/model/group_resource_meta.py
fds/sdk/ProcuretoPaySCIM/model/group_resource_urn_scim_schemas_extension_fact_set_enterprise_hosting10_group.py
fds/sdk/ProcuretoPaySCIM/model/location_resource.py
fds/sdk/ProcuretoPaySCIM/model/location_resource_list.py
fds/sdk/ProcuretoPaySCIM/model/location_resource_meta.py
fds/sdk/ProcuretoPaySCIM/model/location_resource_reference.py
fds/sdk/ProcuretoPaySCIM/model/patch.py
fds/sdk/ProcuretoPaySCIM/model/patch_operations.py
fds/sdk/ProcuretoPaySCIM/model/pending_product_order.py
fds/sdk/ProcuretoPaySCIM/model/product_resource.py
fds/sdk/ProcuretoPaySCIM/model/product_resource_list.py
fds/sdk/ProcuretoPaySCIM/model/product_resource_meta.py
fds/sdk/ProcuretoPaySCIM/model/product_resource_reference.py
fds/sdk/ProcuretoPaySCIM/model/schema.py
fds/sdk/ProcuretoPaySCIM/model/schema_attributes.py
fds/sdk/ProcuretoPaySCIM/model/schema_list.py
fds/sdk/ProcuretoPaySCIM/model/schema_sub_attributes.py
fds/sdk/ProcuretoPaySCIM/model/service_provider_config.py
fds.sdk.ProcuretoPaySCIM-0.20.0.dist-info/LICENSE
fds.sdk.ProcuretoPaySCIM-0.20.0.dist-info/METADATA
fds.sdk.ProcuretoPaySCIM-0.20.0.dist-info/WHEEL
fds.sdk.ProcuretoPaySCIM-0.20.0.dist-info/top_level.txt
fds.sdk.ProcuretoPaySCIM-0.20.0.dist-info/RECORD
