Metadata-Version: 2.1
Name: fds.sdk.ProcuretoPaySCIM
Version: 0.20.0
Summary: Procure to Pay SCIM client library for Python
Home-page: https://github.com/FactSet/enterprise-sdk/tree/main/code/python/ProcuretoPaySCIM/v1
Author: FactSet Research Systems
License: Apache-2.0
Keywords: FactSet,API,SDK
Platform: UNKNOWN
Requires-Python: >=3.6
License-File: LICENSE
Requires-Dist: urllib3 (>=1.25.3)
Requires-Dist: python-dateutil
Requires-Dist: fds.sdk.utils (>=1.0.0)
